import_export/__init__.py
import_export/admin.py
import_export/django_compat.py
import_export/exceptions.py
import_export/fields.py
import_export/forms.py
import_export/instance_loaders.py
import_export/mixins.py
import_export/models.py
import_export/resources.py
import_export/results.py
import_export/signals.py
import_export/tmp_storages.py
import_export/utils.py
import_export/widgets.py
import_export/formats/__init__.py
import_export/formats/base_formats.py
import_export/locale/ar/LC_MESSAGES/django.mo
import_export/locale/ar/LC_MESSAGES/django.po
import_export/locale/bg/LC_MESSAGES/django.mo
import_export/locale/bg/LC_MESSAGES/django.po
import_export/locale/ca/LC_MESSAGES/django.mo
import_export/locale/ca/LC_MESSAGES/django.po
import_export/locale/cs/LC_MESSAGES/django.mo
import_export/locale/cs/LC_MESSAGES/django.po
import_export/locale/de/LC_MESSAGES/django.mo
import_export/locale/de/LC_MESSAGES/django.po
import_export/locale/es/LC_MESSAGES/django.mo
import_export/locale/es/LC_MESSAGES/django.po
import_export/locale/es_AR/LC_MESSAGES/django.mo
import_export/locale/es_AR/LC_MESSAGES/django.po
import_export/locale/fr/LC_MESSAGES/django.mo
import_export/locale/fr/LC_MESSAGES/django.po
import_export/locale/it/LC_MESSAGES/django.mo
import_export/locale/it/LC_MESSAGES/django.po
import_export/locale/ja/LC_MESSAGES/django.mo
import_export/locale/ja/LC_MESSAGES/django.po
import_export/locale/pl/LC_MESSAGES/django.mo
import_export/locale/pl/LC_MESSAGES/django.po
import_export/locale/pt_BR/LC_MESSAGES/django.mo
import_export/locale/pt_BR/LC_MESSAGES/django.po
import_export/locale/ru/LC_MESSAGES/django.mo
import_export/locale/ru/LC_MESSAGES/django.po
import_export/locale/sk/LC_MESSAGES/django.mo
import_export/locale/sk/LC_MESSAGES/django.po
import_export/locale/zh_Hans/LC_MESSAGES/django.mo
import_export/locale/zh_Hans/LC_MESSAGES/django.po
import_export/static/import_export/action_formats.js
import_export/static/import_export/import.css
django_import_export_customized-1.1.1.dev0.dist-info/LICENSE
django_import_export_customized-1.1.1.dev0.dist-info/METADATA
django_import_export_customized-1.1.1.dev0.dist-info/WHEEL
django_import_export_customized-1.1.1.dev0.dist-info/top_level.txt
django_import_export_customized-1.1.1.dev0.dist-info/RECORD
